eagle/__init__.py
eagle/bin/cli.py
eagle/enums.py
eagle/exceptions.py
eagle/faker/__init__.py
eagle/faker/bases.py
eagle/faker/constraint.py
eagle/faker/enums.py
eagle/faker/fields.py
eagle/faker/invalid.py
eagle/faker/managers.py
eagle/http/auth.py
eagle/http/client.py
eagle/http/enums.py
eagle/http/hooks.py
eagle/logger.py
eagle/repoter/excel.py
eagle/repoter/html.py
eagle/runner.py
eagle/settings/bases.py
eagle/testcase/__init__.py
eagle/testcase/bases.py
eagle/testcase/check_points/bases.py
eagle/testcase/check_points/http.py
eagle/testcase/context.py
eagle/testcase/evaluator.py
eagle/testcase/loader/excel.py
eagle/testcase/loader/module.py
eagle/testcase/loader/yaml.py
eagle/testcase/registry.py
eagle/testcase/rest_caseset.py
eagle/testcase/suitus.py
eagle/testcase/unit.py
eagle/utils.py
api_eagle-0.1.2.dist-info/METADATA
api_eagle-0.1.2.dist-info/WHEEL
api_eagle-0.1.2.dist-info/entry_points.txt
api_eagle-0.1.2.dist-info/RECORD
