Metadata-Version: 2.1
Name: api-eagle
Version: 0.1.2
Summary: 
Home-page: https://github.com/mnioc/eagle.git
License: MIT
Author: juqi.peng
Author-email: pengjuqi@163.com
Requires-Python: >=3.10.4,<4.0.0
Classifier: Development Status :: 3 - Alpha
Classifier: Intended Audience :: Developers
Classifier: License :: OSI Approved :: MIT License
Classifier: Operating System :: OS Independent
Classifier: Programming Language :: Python :: 3
Classifier: Programming Language :: Python :: 3.11
Classifier: Programming Language :: Python :: 3.10
Classifier: Programming Language :: Python :: Implementation :: CPython
Classifier: Programming Language :: Python :: Implementation :: PyPy
Classifier: Programming Language :: Python :: Implementation :: Stackless
Classifier: Topic :: Software Development :: Libraries :: Python Modules
Classifier: Topic :: Utilities
Requires-Dist: click (>=8.1.3,<9.0.0)
Requires-Dist: colorama (>=0.4.6,<0.5.0)
Requires-Dist: colorlog (>=6.7.0,<7.0.0)
Requires-Dist: ipython (>=8.15.0,<9.0.0)
Requires-Dist: jsonpath-ng (>=1.5.3,<2.0.0)
Requires-Dist: jsonpath-rw (>=1.4.0,<2.0.0)
Requires-Dist: loguru (>=0.6.0,<0.7.0)
Requires-Dist: prettytable (>=3.8.0,<4.0.0)
Requires-Dist: pytz (>=2023.3.post1,<2024.0)
Requires-Dist: pyyaml (>=6.0,<7.0)
Requires-Dist: requests (>=2.26.0,<3.0.0)
